electivity/__init__.py
electivity/electivity.py
electivity-2.0.0.dist-info/LICENSE
electivity-2.0.0.dist-info/METADATA
electivity-2.0.0.dist-info/WHEEL
electivity-2.0.0.dist-info/top_level.txt
electivity-2.0.0.dist-info/RECORD
