Metadata-Version: 2.1
Name: electivity
Version: 2.0.0
Summary: Ecological electivity and forage indices
Home-page: https://github.com/aazuspan/electivity
Author: Aaron Zuspan
Author-email: aa.zuspan@gmail.com
License: UNKNOWN
Project-URL: Bug Reports, https://github.com/aazuspan/electivity/issues
Project-URL: Source, https://github.com/aazuspan/electivity/
Keywords: electivity ecology biology selectivity
Platform: UNKNOWN
Classifier: Development Status :: 3 - Alpha
Classifier: Intended Audience :: Science/Research
Classifier: Topic :: Scientific/Engineering :: Bio-Informatics
Classifier: License :: OSI Approved :: MIT License
Classifier: Programming Language :: Python :: 3
Classifier: Programming Language :: Python :: 3.5
Classifier: Programming Language :: Python :: 3.6
Classifier: Programming Language :: Python :: 3.7
Requires-Python: >=2.7, !=3.0.*, !=3.1.*, !=3.2.*, !=3.3.*, !=3.4.*, <4
Requires-Dist: pandas (==1.2.2)
Requires-Dist: pytz (==2021.1)
Requires-Dist: python-dateutil (==2.8.1) ; python_version >= "2.7" and python_version not in "3.0, 3.1, 3.2, 3.3"
Requires-Dist: six (==1.15.0) ; python_version >= "2.7" and python_version not in "3.0, 3.1, 3.2, 3.3"
Requires-Dist: numpy (==1.20.1) ; python_version >= "3.7"
Provides-Extra: dev
